planet_smt/__init__.py
planet_smt/utils.py
planet_smt/models/__init__.py
planet_smt/models/base.py
planet_smt/models/scope.py
planet_smt/models/state.py
planet_smt/models/workflow.py
planet_smt/models/markers/__init__.py
planet_smt/models/markers/main.py
planet_smt/models/markers/marker_config/__init__.py
planet_smt/models/markers/marker_config/baresoil.py
planet_smt/models/markers/marker_config/base.py
planet_smt/models/markers/marker_config/classification.py
planet_smt/models/markers/marker_config/distance.py
planet_smt/models/markers/marker_config/greening_harvest.py
planet_smt/models/markers/marker_config/homogeneity.py
planet_smt/models/markers/marker_config/mean_ndvi.py
planet_smt/models/markers/marker_config/mowing.py
planet_smt/models/markers/marker_config/ploughing.py
planet_smt/models/markers/marker_config/similarity.py
planet_smt/models/markers/marker_config/utils.py
planet_smt/sdk/__init__.py
planet_smt/sdk/client.py
planet_smt-24.9.2.dist-info/LICENSE
planet_smt-24.9.2.dist-info/METADATA
planet_smt-24.9.2.dist-info/WHEEL
planet_smt-24.9.2.dist-info/top_level.txt
planet_smt-24.9.2.dist-info/RECORD
