Metadata-Version: 2.1
Name: planet-smt
Version: 24.9.2
Summary: SDK of Signals and Markers Toolkit
Author: Planet Labs
Requires-Python: >=3.11
License-File: LICENSE
Requires-Dist: pydantic <2.0
Requires-Dist: httpx
Requires-Dist: backoff
